package com.google.android.gms.internal;

import android.os.Binder;
import android.os.Bundle;
import android.os.IBinder;
import android.os.IInterface;
import android.os.Parcel;
import android.os.Parcelable.Creator;
import android.os.RemoteException;

public abstract interface dp
  extends IInterface
{
  public abstract void a(do paramdo, int paramInt)
    throws RemoteException;
  
  public abstract void a(do paramdo, int paramInt, String paramString)
    throws RemoteException;
  
  public abstract void a(do paramdo, int paramInt, String paramString, Bundle paramBundle)
    throws RemoteException;
  
  public abstract void a(do paramdo, int paramInt, String paramString1, String paramString2, String[] paramArrayOfString)
    throws RemoteException;
  
  public abstract void a(do paramdo, int paramInt, String paramString1, String paramString2, String[] paramArrayOfString, String paramString3, Bundle paramBundle)
    throws RemoteException;
  
  public abstract void a(do paramdo, int paramInt, String paramString1, String paramString2, String[] paramArrayOfString, String paramString3, IBinder paramIBinder, String paramString4, Bundle paramBundle)
    throws RemoteException;
  
  public abstract void b(do paramdo, int paramInt, String paramString, Bundle paramBundle)
    throws RemoteException;
  
  public abstract void c(do paramdo, int paramInt, String paramString, Bundle paramBundle)
    throws RemoteException;
  
  public abstract void d(do paramdo, int paramInt, String paramString, Bundle paramBundle)
    throws RemoteException;
  
  public abstract void e(do paramdo, int paramInt, String paramString, Bundle paramBundle)
    throws RemoteException;
  
  public abstract void f(do paramdo, int paramInt, String paramString, Bundle paramBundle)
    throws RemoteException;
  
  public abstract void g(do paramdo, int paramInt, String paramString, Bundle paramBundle)
    throws RemoteException;
  
  public abstract void h(do paramdo, int paramInt, String paramString, Bundle paramBundle)
    throws RemoteException;
  
  public abstract void i(do paramdo, int paramInt, String paramString, Bundle paramBundle)
    throws RemoteException;
  
  public abstract void j(do paramdo, int paramInt, String paramString, Bundle paramBundle)
    throws RemoteException;
  
  public static abstract class a
    extends Binder
    implements dp
  {
    public static dp F(IBinder paramIBinder)
    {
      if (paramIBinder == null) {
        return null;
      }
      IInterface localIInterface = paramIBinder.queryLocalInterface("com.google.android.gms.common.internal.IGmsServiceBroker");
      if ((localIInterface != null) && ((localIInterface instanceof dp))) {
        return (dp)localIInterface;
      }
      return new a(paramIBinder);
    }
    
    public boolean onTransact(int paramInt1, Parcel paramParcel1, Parcel paramParcel2, int paramInt2)
      throws RemoteException
    {
      switch (paramInt1)
      {
      default: 
        return super.onTransact(paramInt1, paramParcel1, paramParcel2, paramInt2);
      case 1598968902: 
        paramParcel2.writeString("com.google.android.gms.common.internal.IGmsServiceBroker");
        return true;
      case 1: 
        paramParcel1.enforceInterface("com.google.android.gms.common.internal.IGmsServiceBroker");
        do localdo12 = do.a.E(paramParcel1.readStrongBinder());
        int i17 = paramParcel1.readInt();
        String str15 = paramParcel1.readString();
        String str16 = paramParcel1.readString();
        String[] arrayOfString2 = paramParcel1.createStringArray();
        String str17 = paramParcel1.readString();
        if (paramParcel1.readInt() != 0) {}
        for (Bundle localBundle12 = (Bundle)Bundle.CREATOR.createFromParcel(paramParcel1);; localBundle12 = null)
        {
          a(localdo12, i17, str15, str16, arrayOfString2, str17, localBundle12);
          paramParcel2.writeNoException();
          return true;
        }
      case 2: 
        paramParcel1.enforceInterface("com.google.android.gms.common.internal.IGmsServiceBroker");
        do localdo11 = do.a.E(paramParcel1.readStrongBinder());
        int i15 = paramParcel1.readInt();
        String str14 = paramParcel1.readString();
        int i16 = paramParcel1.readInt();
        Bundle localBundle11 = null;
        if (i16 != 0) {
          localBundle11 = (Bundle)Bundle.CREATOR.createFromParcel(paramParcel1);
        }
        a(localdo11, i15, str14, localBundle11);
        paramParcel2.writeNoException();
        return true;
      case 3: 
        paramParcel1.enforceInterface("com.google.android.gms.common.internal.IGmsServiceBroker");
        a(do.a.E(paramParcel1.readStrongBinder()), paramParcel1.readInt(), paramParcel1.readString());
        paramParcel2.writeNoException();
        return true;
      case 4: 
        paramParcel1.enforceInterface("com.google.android.gms.common.internal.IGmsServiceBroker");
        a(do.a.E(paramParcel1.readStrongBinder()), paramParcel1.readInt());
        paramParcel2.writeNoException();
        return true;
      case 5: 
        paramParcel1.enforceInterface("com.google.android.gms.common.internal.IGmsServiceBroker");
        do localdo10 = do.a.E(paramParcel1.readStrongBinder());
        int i13 = paramParcel1.readInt();
        String str13 = paramParcel1.readString();
        int i14 = paramParcel1.readInt();
        Bundle localBundle10 = null;
        if (i14 != 0) {
          localBundle10 = (Bundle)Bundle.CREATOR.createFromParcel(paramParcel1);
        }
        b(localdo10, i13, str13, localBundle10);
        paramParcel2.writeNoException();
        return true;
      case 6: 
        paramParcel1.enforceInterface("com.google.android.gms.common.internal.IGmsServiceBroker");
        do localdo9 = do.a.E(paramParcel1.readStrongBinder());
        int i11 = paramParcel1.readInt();
        String str12 = paramParcel1.readString();
        int i12 = paramParcel1.readInt();
        Bundle localBundle9 = null;
        if (i12 != 0) {
          localBundle9 = (Bundle)Bundle.CREATOR.createFromParcel(paramParcel1);
        }
        c(localdo9, i11, str12, localBundle9);
        paramParcel2.writeNoException();
        return true;
      case 7: 
        paramParcel1.enforceInterface("com.google.android.gms.common.internal.IGmsServiceBroker");
        do localdo8 = do.a.E(paramParcel1.readStrongBinder());
        int i9 = paramParcel1.readInt();
        String str11 = paramParcel1.readString();
        int i10 = paramParcel1.readInt();
        Bundle localBundle8 = null;
        if (i10 != 0) {
          localBundle8 = (Bundle)Bundle.CREATOR.createFromParcel(paramParcel1);
        }
        d(localdo8, i9, str11, localBundle8);
        paramParcel2.writeNoException();
        return true;
      case 8: 
        paramParcel1.enforceInterface("com.google.android.gms.common.internal.IGmsServiceBroker");
        do localdo7 = do.a.E(paramParcel1.readStrongBinder());
        int i7 = paramParcel1.readInt();
        String str10 = paramParcel1.readString();
        int i8 = paramParcel1.readInt();
        Bundle localBundle7 = null;
        if (i8 != 0) {
          localBundle7 = (Bundle)Bundle.CREATOR.createFromParcel(paramParcel1);
        }
        e(localdo7, i7, str10, localBundle7);
        paramParcel2.writeNoException();
        return true;
      case 9: 
        paramParcel1.enforceInterface("com.google.android.gms.common.internal.IGmsServiceBroker");
        do localdo6 = do.a.E(paramParcel1.readStrongBinder());
        int i6 = paramParcel1.readInt();
        String str6 = paramParcel1.readString();
        String str7 = paramParcel1.readString();
        String[] arrayOfString1 = paramParcel1.createStringArray();
        String str8 = paramParcel1.readString();
        IBinder localIBinder = paramParcel1.readStrongBinder();
        String str9 = paramParcel1.readString();
        if (paramParcel1.readInt() != 0) {}
        for (Bundle localBundle6 = (Bundle)Bundle.CREATOR.createFromParcel(paramParcel1);; localBundle6 = null)
        {
          a(localdo6, i6, str6, str7, arrayOfString1, str8, localIBinder, str9, localBundle6);
          paramParcel2.writeNoException();
          return true;
        }
      case 10: 
        paramParcel1.enforceInterface("com.google.android.gms.common.internal.IGmsServiceBroker");
        a(do.a.E(paramParcel1.readStrongBinder()), paramParcel1.readInt(), paramParcel1.readString(), paramParcel1.readString(), paramParcel1.createStringArray());
        paramParcel2.writeNoException();
        return true;
      case 11: 
        paramParcel1.enforceInterface("com.google.android.gms.common.internal.IGmsServiceBroker");
        do localdo5 = do.a.E(paramParcel1.readStrongBinder());
        int i4 = paramParcel1.readInt();
        String str5 = paramParcel1.readString();
        int i5 = paramParcel1.readInt();
        Bundle localBundle5 = null;
        if (i5 != 0) {
          localBundle5 = (Bundle)Bundle.CREATOR.createFromParcel(paramParcel1);
        }
        f(localdo5, i4, str5, localBundle5);
        paramParcel2.writeNoException();
        return true;
      case 12: 
        paramParcel1.enforceInterface("com.google.android.gms.common.internal.IGmsServiceBroker");
        do localdo4 = do.a.E(paramParcel1.readStrongBinder());
        int i2 = paramParcel1.readInt();
        String str4 = paramParcel1.readString();
        int i3 = paramParcel1.readInt();
        Bundle localBundle4 = null;
        if (i3 != 0) {
          localBundle4 = (Bundle)Bundle.CREATOR.createFromParcel(paramParcel1);
        }
        g(localdo4, i2, str4, localBundle4);
        paramParcel2.writeNoException();
        return true;
      case 13: 
        paramParcel1.enforceInterface("com.google.android.gms.common.internal.IGmsServiceBroker");
        do localdo3 = do.a.E(paramParcel1.readStrongBinder());
        int n = paramParcel1.readInt();
        String str3 = paramParcel1.readString();
        int i1 = paramParcel1.readInt();
        Bundle localBundle3 = null;
        if (i1 != 0) {
          localBundle3 = (Bundle)Bundle.CREATOR.createFromParcel(paramParcel1);
        }
        h(localdo3, n, str3, localBundle3);
        paramParcel2.writeNoException();
        return true;
      case 14: 
        paramParcel1.enforceInterface("com.google.android.gms.common.internal.IGmsServiceBroker");
        do localdo2 = do.a.E(paramParcel1.readStrongBinder());
        int k = paramParcel1.readInt();
        String str2 = paramParcel1.readString();
        int m = paramParcel1.readInt();
        Bundle localBundle2 = null;
        if (m != 0) {
          localBundle2 = (Bundle)Bundle.CREATOR.createFromParcel(paramParcel1);
        }
        i(localdo2, k, str2, localBundle2);
        paramParcel2.writeNoException();
        return true;
      }
      paramParcel1.enforceInterface("com.google.android.gms.common.internal.IGmsServiceBroker");
      do localdo1 = do.a.E(paramParcel1.readStrongBinder());
      int i = paramParcel1.readInt();
      String str1 = paramParcel1.readString();
      int j = paramParcel1.readInt();
      Bundle localBundle1 = null;
      if (j != 0) {
        localBundle1 = (Bundle)Bundle.CREATOR.createFromParcel(paramParcel1);
      }
      j(localdo1, i, str1, localBundle1);
      paramParcel2.writeNoException();
      return true;
    }
    
    private static class a
      implements dp
    {
      private IBinder dG;
      
      a(IBinder paramIBinder)
      {
        this.dG = paramIBinder;
      }
      
      /* Error */
      public void a(do paramdo, int paramInt)
        throws RemoteException
      {
        // Byte code:
        //   0: invokestatic 25	android/os/Parcel:obtain	()Landroid/os/Parcel;
        //   3: astore_3
        //   4: invokestatic 25	android/os/Parcel:obtain	()Landroid/os/Parcel;
        //   7: astore 4
        //   9: aload_3
        //   10: ldc 27
        //   12: invokevirtual 31	android/os/Parcel:writeInterfaceToken	(Ljava/lang/String;)V
        //   15: aload_1
        //   16: ifnull +52 -> 68
        //   19: aload_1
        //   20: invokeinterface 37 1 0
        //   25: astore 6
        //   27: aload_3
        //   28: aload 6
        //   30: invokevirtual 40	android/os/Parcel:writeStrongBinder	(Landroid/os/IBinder;)V
        //   33: aload_3
        //   34: iload_2
        //   35: invokevirtual 44	android/os/Parcel:writeInt	(I)V
        //   38: aload_0
        //   39: getfield 15	com/google/android/gms/internal/dp$a$a:dG	Landroid/os/IBinder;
        //   42: iconst_4
        //   43: aload_3
        //   44: aload 4
        //   46: iconst_0
        //   47: invokeinterface 50 5 0
        //   52: pop
        //   53: aload 4
        //   55: invokevirtual 53	android/os/Parcel:readException	()V
        //   58: aload 4
        //   60: invokevirtual 56	android/os/Parcel:recycle	()V
        //   63: aload_3
        //   64: invokevirtual 56	android/os/Parcel:recycle	()V
        //   67: return
        //   68: aconst_null
        //   69: astore 6
        //   71: goto -44 -> 27
        //   74: astore 5
        //   76: aload 4
        //   78: invokevirtual 56	android/os/Parcel:recycle	()V
        //   81: aload_3
        //   82: invokevirtual 56	android/os/Parcel:recycle	()V
        //   85: aload 5
        //   87: athrow
        // Local variable table:
        //   start	length	slot	name	signature
        //   0	88	0	this	a
        //   0	88	1	paramdo	do
        //   0	88	2	paramInt	int
        //   3	79	3	localParcel1	Parcel
        //   7	70	4	localParcel2	Parcel
        //   74	12	5	localObject	Object
        //   25	45	6	localIBinder	IBinder
        // Exception table:
        //   from	to	target	type
        //   9	15	74	finally
        //   19	27	74	finally
        //   27	58	74	finally
      }
      
      /* Error */
      public void a(do paramdo, int paramInt, String paramString)
        throws RemoteException
      {
        // Byte code:
        //   0: invokestatic 25	android/os/Parcel:obtain	()Landroid/os/Parcel;
        //   3: astore 4
        //   5: invokestatic 25	android/os/Parcel:obtain	()Landroid/os/Parcel;
        //   8: astore 5
        //   10: aload 4
        //   12: ldc 27
        //   14: invokevirtual 31	android/os/Parcel:writeInterfaceToken	(Ljava/lang/String;)V
        //   17: aload_1
        //   18: ifnull +62 -> 80
        //   21: aload_1
        //   22: invokeinterface 37 1 0
        //   27: astore 7
        //   29: aload 4
        //   31: aload 7
        //   33: invokevirtual 40	android/os/Parcel:writeStrongBinder	(Landroid/os/IBinder;)V
        //   36: aload 4
        //   38: iload_2
        //   39: invokevirtual 44	android/os/Parcel:writeInt	(I)V
        //   42: aload 4
        //   44: aload_3
        //   45: invokevirtual 60	android/os/Parcel:writeString	(Ljava/lang/String;)V
        //   48: aload_0
        //   49: getfield 15	com/google/android/gms/internal/dp$a$a:dG	Landroid/os/IBinder;
        //   52: iconst_3
        //   53: aload 4
        //   55: aload 5
        //   57: iconst_0
        //   58: invokeinterface 50 5 0
        //   63: pop
        //   64: aload 5
        //   66: invokevirtual 53	android/os/Parcel:readException	()V
        //   69: aload 5
        //   71: invokevirtual 56	android/os/Parcel:recycle	()V
        //   74: aload 4
        //   76: invokevirtual 56	android/os/Parcel:recycle	()V
        //   79: return
        //   80: aconst_null
        //   81: astore 7
        //   83: goto -54 -> 29
        //   86: astore 6
        //   88: aload 5
        //   90: invokevirtual 56	android/os/Parcel:recycle	()V
        //   93: aload 4
        //   95: invokevirtual 56	android/os/Parcel:recycle	()V
        //   98: aload 6
        //   100: athrow
        // Local variable table:
        //   start	length	slot	name	signature
        //   0	101	0	this	a
        //   0	101	1	paramdo	do
        //   0	101	2	paramInt	int
        //   0	101	3	paramString	String
        //   3	91	4	localParcel1	Parcel
        //   8	81	5	localParcel2	Parcel
        //   86	13	6	localObject	Object
        //   27	55	7	localIBinder	IBinder
        // Exception table:
        //   from	to	target	type
        //   10	17	86	finally
        //   21	29	86	finally
        //   29	69	86	finally
      }
      
      /* Error */
      public void a(do paramdo, int paramInt, String paramString, Bundle paramBundle)
        throws RemoteException
      {
        // Byte code:
        //   0: invokestatic 25	android/os/Parcel:obtain	()Landroid/os/Parcel;
        //   3: astore 5
        //   5: invokestatic 25	android/os/Parcel:obtain	()Landroid/os/Parcel;
        //   8: astore 6
        //   10: aload 5
        //   12: ldc 27
        //   14: invokevirtual 31	android/os/Parcel:writeInterfaceToken	(Ljava/lang/String;)V
        //   17: aload_1
        //   18: ifnull +81 -> 99
        //   21: aload_1
        //   22: invokeinterface 37 1 0
        //   27: astore 8
        //   29: aload 5
        //   31: aload 8
        //   33: invokevirtual 40	android/os/Parcel:writeStrongBinder	(Landroid/os/IBinder;)V
        //   36: aload 5
        //   38: iload_2
        //   39: invokevirtual 44	android/os/Parcel:writeInt	(I)V
        //   42: aload 5
        //   44: aload_3
        //   45: invokevirtual 60	android/os/Parcel:writeString	(Ljava/lang/String;)V
        //   48: aload 4
        //   50: ifnull +55 -> 105
        //   53: aload 5
        //   55: iconst_1
        //   56: invokevirtual 44	android/os/Parcel:writeInt	(I)V
        //   59: aload 4
        //   61: aload 5
        //   63: iconst_0
        //   64: invokevirtual 67	android/os/Bundle:writeToParcel	(Landroid/os/Parcel;I)V
        //   67: aload_0
        //   68: getfield 15	com/google/android/gms/internal/dp$a$a:dG	Landroid/os/IBinder;
        //   71: iconst_2
        //   72: aload 5
        //   74: aload 6
        //   76: iconst_0
        //   77: invokeinterface 50 5 0
        //   82: pop
        //   83: aload 6
        //   85: invokevirtual 53	android/os/Parcel:readException	()V
        //   88: aload 6
        //   90: invokevirtual 56	android/os/Parcel:recycle	()V
        //   93: aload 5
        //   95: invokevirtual 56	android/os/Parcel:recycle	()V
        //   98: return
        //   99: aconst_null
        //   100: astore 8
        //   102: goto -73 -> 29
        //   105: aload 5
        //   107: iconst_0
        //   108: invokevirtual 44	android/os/Parcel:writeInt	(I)V
        //   111: goto -44 -> 67
        //   114: astore 7
        //   116: aload 6
        //   118: invokevirtual 56	android/os/Parcel:recycle	()V
        //   121: aload 5
        //   123: invokevirtual 56	android/os/Parcel:recycle	()V
        //   126: aload 7
        //   128: athrow
        // Local variable table:
        //   start	length	slot	name	signature
        //   0	129	0	this	a
        //   0	129	1	paramdo	do
        //   0	129	2	paramInt	int
        //   0	129	3	paramString	String
        //   0	129	4	paramBundle	Bundle
        //   3	119	5	localParcel1	Parcel
        //   8	109	6	localParcel2	Parcel
        //   114	13	7	localObject	Object
        //   27	74	8	localIBinder	IBinder
        // Exception table:
        //   from	to	target	type
        //   10	17	114	finally
        //   21	29	114	finally
        //   29	48	114	finally
        //   53	67	114	finally
        //   67	88	114	finally
        //   105	111	114	finally
      }
      
      /* Error */
      public void a(do paramdo, int paramInt, String paramString1, String paramString2, String[] paramArrayOfString)
        throws RemoteException
      {
        // Byte code:
        //   0: invokestatic 25	android/os/Parcel:obtain	()Landroid/os/Parcel;
        //   3: astore 6
        //   5: invokestatic 25	android/os/Parcel:obtain	()Landroid/os/Parcel;
        //   8: astore 7
        //   10: aload 6
        //   12: ldc 27
        //   14: invokevirtual 31	android/os/Parcel:writeInterfaceToken	(Ljava/lang/String;)V
        //   17: aload_1
        //   18: ifnull +77 -> 95
        //   21: aload_1
        //   22: invokeinterface 37 1 0
        //   27: astore 9
        //   29: aload 6
        //   31: aload 9
        //   33: invokevirtual 40	android/os/Parcel:writeStrongBinder	(Landroid/os/IBinder;)V
        //   36: aload 6
        //   38: iload_2
        //   39: invokevirtual 44	android/os/Parcel:writeInt	(I)V
        //   42: aload 6
        //   44: aload_3
        //   45: invokevirtual 60	android/os/Parcel:writeString	(Ljava/lang/String;)V
        //   48: aload 6
        //   50: aload 4
        //   52: invokevirtual 60	android/os/Parcel:writeString	(Ljava/lang/String;)V
        //   55: aload 6
        //   57: aload 5
        //   59: invokevirtual 72	android/os/Parcel:writeStringArray	([Ljava/lang/String;)V
        //   62: aload_0
        //   63: getfield 15	com/google/android/gms/internal/dp$a$a:dG	Landroid/os/IBinder;
        //   66: bipush 10
        //   68: aload 6
        //   70: aload 7
        //   72: iconst_0
        //   73: invokeinterface 50 5 0
        //   78: pop
        //   79: aload 7
        //   81: invokevirtual 53	android/os/Parcel:readException	()V
        //   84: aload 7
        //   86: invokevirtual 56	android/os/Parcel:recycle	()V
        //   89: aload 6
        //   91: invokevirtual 56	android/os/Parcel:recycle	()V
        //   94: return
        //   95: aconst_null
        //   96: astore 9
        //   98: goto -69 -> 29
        //   101: astore 8
        //   103: aload 7
        //   105: invokevirtual 56	android/os/Parcel:recycle	()V
        //   108: aload 6
        //   110: invokevirtual 56	android/os/Parcel:recycle	()V
        //   113: aload 8
        //   115: athrow
        // Local variable table:
        //   start	length	slot	name	signature
        //   0	116	0	this	a
        //   0	116	1	paramdo	do
        //   0	116	2	paramInt	int
        //   0	116	3	paramString1	String
        //   0	116	4	paramString2	String
        //   0	116	5	paramArrayOfString	String[]
        //   3	106	6	localParcel1	Parcel
        //   8	96	7	localParcel2	Parcel
        //   101	13	8	localObject	Object
        //   27	70	9	localIBinder	IBinder
        // Exception table:
        //   from	to	target	type
        //   10	17	101	finally
        //   21	29	101	finally
        //   29	84	101	finally
      }
      
      /* Error */
      public void a(do paramdo, int paramInt, String paramString1, String paramString2, String[] paramArrayOfString, String paramString3, Bundle paramBundle)
        throws RemoteException
      {
        // Byte code:
        //   0: invokestatic 25	android/os/Parcel:obtain	()Landroid/os/Parcel;
        //   3: astore 8
        //   5: invokestatic 25	android/os/Parcel:obtain	()Landroid/os/Parcel;
        //   8: astore 9
        //   10: aload 8
        //   12: ldc 27
        //   14: invokevirtual 31	android/os/Parcel:writeInterfaceToken	(Ljava/lang/String;)V
        //   17: aload_1
        //   18: ifnull +102 -> 120
        //   21: aload_1
        //   22: invokeinterface 37 1 0
        //   27: astore 11
        //   29: aload 8
        //   31: aload 11
        //   33: invokevirtual 40	android/os/Parcel:writeStrongBinder	(Landroid/os/IBinder;)V
        //   36: aload 8
        //   38: iload_2
        //   39: invokevirtual 44	android/os/Parcel:writeInt	(I)V
        //   42: aload 8
        //   44: aload_3
        //   45: invokevirtual 60	android/os/Parcel:writeString	(Ljava/lang/String;)V
        //   48: aload 8
        //   50: aload 4
        //   52: invokevirtual 60	android/os/Parcel:writeString	(Ljava/lang/String;)V
        //   55: aload 8
        //   57: aload 5
        //   59: invokevirtual 72	android/os/Parcel:writeStringArray	([Ljava/lang/String;)V
        //   62: aload 8
        //   64: aload 6
        //   66: invokevirtual 60	android/os/Parcel:writeString	(Ljava/lang/String;)V
        //   69: aload 7
        //   71: ifnull +55 -> 126
        //   74: aload 8
        //   76: iconst_1
        //   77: invokevirtual 44	android/os/Parcel:writeInt	(I)V
        //   80: aload 7
        //   82: aload 8
        //   84: iconst_0
        //   85: invokevirtual 67	android/os/Bundle:writeToParcel	(Landroid/os/Parcel;I)V
        //   88: aload_0
        //   89: getfield 15	com/google/android/gms/internal/dp$a$a:dG	Landroid/os/IBinder;
        //   92: iconst_1
        //   93: aload 8
        //   95: aload 9
        //   97: iconst_0
        //   98: invokeinterface 50 5 0
        //   103: pop
        //   104: aload 9
        //   106: invokevirtual 53	android/os/Parcel:readException	()V
        //   109: aload 9
        //   111: invokevirtual 56	android/os/Parcel:recycle	()V
        //   114: aload 8
        //   116: invokevirtual 56	android/os/Parcel:recycle	()V
        //   119: return
        //   120: aconst_null
        //   121: astore 11
        //   123: goto -94 -> 29
        //   126: aload 8
        //   128: iconst_0
        //   129: invokevirtual 44	android/os/Parcel:writeInt	(I)V
        //   132: goto -44 -> 88
        //   135: astore 10
        //   137: aload 9
        //   139: invokevirtual 56	android/os/Parcel:recycle	()V
        //   142: aload 8
        //   144: invokevirtual 56	android/os/Parcel:recycle	()V
        //   147: aload 10
        //   149: athrow
        // Local variable table:
        //   start	length	slot	name	signature
        //   0	150	0	this	a
        //   0	150	1	paramdo	do
        //   0	150	2	paramInt	int
        //   0	150	3	paramString1	String
        //   0	150	4	paramString2	String
        //   0	150	5	paramArrayOfString	String[]
        //   0	150	6	paramString3	String
        //   0	150	7	paramBundle	Bundle
        //   3	140	8	localParcel1	Parcel
        //   8	130	9	localParcel2	Parcel
        //   135	13	10	localObject	Object
        //   27	95	11	localIBinder	IBinder
        // Exception table:
        //   from	to	target	type
        //   10	17	135	finally
        //   21	29	135	finally
        //   29	69	135	finally
        //   74	88	135	finally
        //   88	109	135	finally
        //   126	132	135	finally
      }
      
      /* Error */
      public void a(do paramdo, int paramInt, String paramString1, String paramString2, String[] paramArrayOfString, String paramString3, IBinder paramIBinder, String paramString4, Bundle paramBundle)
        throws RemoteException
      {
        // Byte code:
        //   0: invokestatic 25	android/os/Parcel:obtain	()Landroid/os/Parcel;
        //   3: astore 10
        //   5: invokestatic 25	android/os/Parcel:obtain	()Landroid/os/Parcel;
        //   8: astore 11
        //   10: aload 10
        //   12: ldc 27
        //   14: invokevirtual 31	android/os/Parcel:writeInterfaceToken	(Ljava/lang/String;)V
        //   17: aload_1
        //   18: ifnull +117 -> 135
        //   21: aload_1
        //   22: invokeinterface 37 1 0
        //   27: astore 13
        //   29: aload 10
        //   31: aload 13
        //   33: invokevirtual 40	android/os/Parcel:writeStrongBinder	(Landroid/os/IBinder;)V
        //   36: aload 10
        //   38: iload_2
        //   39: invokevirtual 44	android/os/Parcel:writeInt	(I)V
        //   42: aload 10
        //   44: aload_3
        //   45: invokevirtual 60	android/os/Parcel:writeString	(Ljava/lang/String;)V
        //   48: aload 10
        //   50: aload 4
        //   52: invokevirtual 60	android/os/Parcel:writeString	(Ljava/lang/String;)V
        //   55: aload 10
        //   57: aload 5
        //   59: invokevirtual 72	android/os/Parcel:writeStringArray	([Ljava/lang/String;)V
        //   62: aload 10
        //   64: aload 6
        //   66: invokevirtual 60	android/os/Parcel:writeString	(Ljava/lang/String;)V
        //   69: aload 10
        //   71: aload 7
        //   73: invokevirtual 40	android/os/Parcel:writeStrongBinder	(Landroid/os/IBinder;)V
        //   76: aload 10
        //   78: aload 8
        //   80: invokevirtual 60	android/os/Parcel:writeString	(Ljava/lang/String;)V
        //   83: aload 9
        //   85: ifnull +56 -> 141
        //   88: aload 10
        //   90: iconst_1
        //   91: invokevirtual 44	android/os/Parcel:writeInt	(I)V
        //   94: aload 9
        //   96: aload 10
        //   98: iconst_0
        //   99: invokevirtual 67	android/os/Bundle:writeToParcel	(Landroid/os/Parcel;I)V
        //   102: aload_0
        //   103: getfield 15	com/google/android/gms/internal/dp$a$a:dG	Landroid/os/IBinder;
        //   106: bipush 9
        //   108: aload 10
        //   110: aload 11
        //   112: iconst_0
        //   113: invokeinterface 50 5 0
        //   118: pop
        //   119: aload 11
        //   121: invokevirtual 53	android/os/Parcel:readException	()V
        //   124: aload 11
        //   126: invokevirtual 56	android/os/Parcel:recycle	()V
        //   129: aload 10
        //   131: invokevirtual 56	android/os/Parcel:recycle	()V
        //   134: return
        //   135: aconst_null
        //   136: astore 13
        //   138: goto -109 -> 29
        //   141: aload 10
        //   143: iconst_0
        //   144: invokevirtual 44	android/os/Parcel:writeInt	(I)V
        //   147: goto -45 -> 102
        //   150: astore 12
        //   152: aload 11
        //   154: invokevirtual 56	android/os/Parcel:recycle	()V
        //   157: aload 10
        //   159: invokevirtual 56	android/os/Parcel:recycle	()V
        //   162: aload 12
        //   164: athrow
        // Local variable table:
        //   start	length	slot	name	signature
        //   0	165	0	this	a
        //   0	165	1	paramdo	do
        //   0	165	2	paramInt	int
        //   0	165	3	paramString1	String
        //   0	165	4	paramString2	String
        //   0	165	5	paramArrayOfString	String[]
        //   0	165	6	paramString3	String
        //   0	165	7	paramIBinder	IBinder
        //   0	165	8	paramString4	String
        //   0	165	9	paramBundle	Bundle
        //   3	155	10	localParcel1	Parcel
        //   8	145	11	localParcel2	Parcel
        //   150	13	12	localObject	Object
        //   27	110	13	localIBinder	IBinder
        // Exception table:
        //   from	to	target	type
        //   10	17	150	finally
        //   21	29	150	finally
        //   29	83	150	finally
        //   88	102	150	finally
        //   102	124	150	finally
        //   141	147	150	finally
      }
      
      public IBinder asBinder()
      {
        return this.dG;
      }
      
      /* Error */
      public void b(do paramdo, int paramInt, String paramString, Bundle paramBundle)
        throws RemoteException
      {
        // Byte code:
        //   0: invokestatic 25	android/os/Parcel:obtain	()Landroid/os/Parcel;
        //   3: astore 5
        //   5: invokestatic 25	android/os/Parcel:obtain	()Landroid/os/Parcel;
        //   8: astore 6
        //   10: aload 5
        //   12: ldc 27
        //   14: invokevirtual 31	android/os/Parcel:writeInterfaceToken	(Ljava/lang/String;)V
        //   17: aload_1
        //   18: ifnull +81 -> 99
        //   21: aload_1
        //   22: invokeinterface 37 1 0
        //   27: astore 8
        //   29: aload 5
        //   31: aload 8
        //   33: invokevirtual 40	android/os/Parcel:writeStrongBinder	(Landroid/os/IBinder;)V
        //   36: aload 5
        //   38: iload_2
        //   39: invokevirtual 44	android/os/Parcel:writeInt	(I)V
        //   42: aload 5
        //   44: aload_3
        //   45: invokevirtual 60	android/os/Parcel:writeString	(Ljava/lang/String;)V
        //   48: aload 4
        //   50: ifnull +55 -> 105
        //   53: aload 5
        //   55: iconst_1
        //   56: invokevirtual 44	android/os/Parcel:writeInt	(I)V
        //   59: aload 4
        //   61: aload 5
        //   63: iconst_0
        //   64: invokevirtual 67	android/os/Bundle:writeToParcel	(Landroid/os/Parcel;I)V
        //   67: aload_0
        //   68: getfield 15	com/google/android/gms/internal/dp$a$a:dG	Landroid/os/IBinder;
        //   71: iconst_5
        //   72: aload 5
        //   74: aload 6
        //   76: iconst_0
        //   77: invokeinterface 50 5 0
        //   82: pop
        //   83: aload 6
        //   85: invokevirtual 53	android/os/Parcel:readException	()V
        //   88: aload 6
        //   90: invokevirtual 56	android/os/Parcel:recycle	()V
        //   93: aload 5
        //   95: invokevirtual 56	android/os/Parcel:recycle	()V
        //   98: return
        //   99: aconst_null
        //   100: astore 8
        //   102: goto -73 -> 29
        //   105: aload 5
        //   107: iconst_0
        //   108: invokevirtual 44	android/os/Parcel:writeInt	(I)V
        //   111: goto -44 -> 67
        //   114: astore 7
        //   116: aload 6
        //   118: invokevirtual 56	android/os/Parcel:recycle	()V
        //   121: aload 5
        //   123: invokevirtual 56	android/os/Parcel:recycle	()V
        //   126: aload 7
        //   128: athrow
        // Local variable table:
        //   start	length	slot	name	signature
        //   0	129	0	this	a
        //   0	129	1	paramdo	do
        //   0	129	2	paramInt	int
        //   0	129	3	paramString	String
        //   0	129	4	paramBundle	Bundle
        //   3	119	5	localParcel1	Parcel
        //   8	109	6	localParcel2	Parcel
        //   114	13	7	localObject	Object
        //   27	74	8	localIBinder	IBinder
        // Exception table:
        //   from	to	target	type
        //   10	17	114	finally
        //   21	29	114	finally
        //   29	48	114	finally
        //   53	67	114	finally
        //   67	88	114	finally
        //   105	111	114	finally
      }
      
      /* Error */
      public void c(do paramdo, int paramInt, String paramString, Bundle paramBundle)
        throws RemoteException
      {
        // Byte code:
        //   0: invokestatic 25	android/os/Parcel:obtain	()Landroid/os/Parcel;
        //   3: astore 5
        //   5: invokestatic 25	android/os/Parcel:obtain	()Landroid/os/Parcel;
        //   8: astore 6
        //   10: aload 5
        //   12: ldc 27
        //   14: invokevirtual 31	android/os/Parcel:writeInterfaceToken	(Ljava/lang/String;)V
        //   17: aload_1
        //   18: ifnull +82 -> 100
        //   21: aload_1
        //   22: invokeinterface 37 1 0
        //   27: astore 8
        //   29: aload 5
        //   31: aload 8
        //   33: invokevirtual 40	android/os/Parcel:writeStrongBinder	(Landroid/os/IBinder;)V
        //   36: aload 5
        //   38: iload_2
        //   39: invokevirtual 44	android/os/Parcel:writeInt	(I)V
        //   42: aload 5
        //   44: aload_3
        //   45: invokevirtual 60	android/os/Parcel:writeString	(Ljava/lang/String;)V
        //   48: aload 4
        //   50: ifnull +56 -> 106
        //   53: aload 5
        //   55: iconst_1
        //   56: invokevirtual 44	android/os/Parcel:writeInt	(I)V
        //   59: aload 4
        //   61: aload 5
        //   63: iconst_0
        //   64: invokevirtual 67	android/os/Bundle:writeToParcel	(Landroid/os/Parcel;I)V
        //   67: aload_0
        //   68: getfield 15	com/google/android/gms/internal/dp$a$a:dG	Landroid/os/IBinder;
        //   71: bipush 6
        //   73: aload 5
        //   75: aload 6
        //   77: iconst_0
        //   78: invokeinterface 50 5 0
        //   83: pop
        //   84: aload 6
        //   86: invokevirtual 53	android/os/Parcel:readException	()V
        //   89: aload 6
        //   91: invokevirtual 56	android/os/Parcel:recycle	()V
        //   94: aload 5
        //   96: invokevirtual 56	android/os/Parcel:recycle	()V
        //   99: return
        //   100: aconst_null
        //   101: astore 8
        //   103: goto -74 -> 29
        //   106: aload 5
        //   108: iconst_0
        //   109: invokevirtual 44	android/os/Parcel:writeInt	(I)V
        //   112: goto -45 -> 67
        //   115: astore 7
        //   117: aload 6
        //   119: invokevirtual 56	android/os/Parcel:recycle	()V
        //   122: aload 5
        //   124: invokevirtual 56	android/os/Parcel:recycle	()V
        //   127: aload 7
        //   129: athrow
        // Local variable table:
        //   start	length	slot	name	signature
        //   0	130	0	this	a
        //   0	130	1	paramdo	do
        //   0	130	2	paramInt	int
        //   0	130	3	paramString	String
        //   0	130	4	paramBundle	Bundle
        //   3	120	5	localParcel1	Parcel
        //   8	110	6	localParcel2	Parcel
        //   115	13	7	localObject	Object
        //   27	75	8	localIBinder	IBinder
        // Exception table:
        //   from	to	target	type
        //   10	17	115	finally
        //   21	29	115	finally
        //   29	48	115	finally
        //   53	67	115	finally
        //   67	89	115	finally
        //   106	112	115	finally
      }
      
      /* Error */
      public void d(do paramdo, int paramInt, String paramString, Bundle paramBundle)
        throws RemoteException
      {
        // Byte code:
        //   0: invokestatic 25	android/os/Parcel:obtain	()Landroid/os/Parcel;
        //   3: astore 5
        //   5: invokestatic 25	android/os/Parcel:obtain	()Landroid/os/Parcel;
        //   8: astore 6
        //   10: aload 5
        //   12: ldc 27
        //   14: invokevirtual 31	android/os/Parcel:writeInterfaceToken	(Ljava/lang/String;)V
        //   17: aload_1
        //   18: ifnull +82 -> 100
        //   21: aload_1
        //   22: invokeinterface 37 1 0
        //   27: astore 8
        //   29: aload 5
        //   31: aload 8
        //   33: invokevirtual 40	android/os/Parcel:writeStrongBinder	(Landroid/os/IBinder;)V
        //   36: aload 5
        //   38: iload_2
        //   39: invokevirtual 44	android/os/Parcel:writeInt	(I)V
        //   42: aload 5
        //   44: aload_3
        //   45: invokevirtual 60	android/os/Parcel:writeString	(Ljava/lang/String;)V
        //   48: aload 4
        //   50: ifnull +56 -> 106
        //   53: aload 5
        //   55: iconst_1
        //   56: invokevirtual 44	android/os/Parcel:writeInt	(I)V
        //   59: aload 4
        //   61: aload 5
        //   63: iconst_0
        //   64: invokevirtual 67	android/os/Bundle:writeToParcel	(Landroid/os/Parcel;I)V
        //   67: aload_0
        //   68: getfield 15	com/google/android/gms/internal/dp$a$a:dG	Landroid/os/IBinder;
        //   71: bipush 7
        //   73: aload 5
        //   75: aload 6
        //   77: iconst_0
        //   78: invokeinterface 50 5 0
        //   83: pop
        //   84: aload 6
        //   86: invokevirtual 53	android/os/Parcel:readException	()V
        //   89: aload 6
        //   91: invokevirtual 56	android/os/Parcel:recycle	()V
        //   94: aload 5
        //   96: invokevirtual 56	android/os/Parcel:recycle	()V
        //   99: return
        //   100: aconst_null
        //   101: astore 8
        //   103: goto -74 -> 29
        //   106: aload 5
        //   108: iconst_0
        //   109: invokevirtual 44	android/os/Parcel:writeInt	(I)V
        //   112: goto -45 -> 67
        //   115: astore 7
        //   117: aload 6
        //   119: invokevirtual 56	android/os/Parcel:recycle	()V
        //   122: aload 5
        //   124: invokevirtual 56	android/os/Parcel:recycle	()V
        //   127: aload 7
        //   129: athrow
        // Local variable table:
        //   start	length	slot	name	signature
        //   0	130	0	this	a
        //   0	130	1	paramdo	do
        //   0	130	2	paramInt	int
        //   0	130	3	paramString	String
        //   0	130	4	paramBundle	Bundle
        //   3	120	5	localParcel1	Parcel
        //   8	110	6	localParcel2	Parcel
        //   115	13	7	localObject	Object
        //   27	75	8	localIBinder	IBinder
        // Exception table:
        //   from	to	target	type
        //   10	17	115	finally
        //   21	29	115	finally
        //   29	48	115	finally
        //   53	67	115	finally
        //   67	89	115	finally
        //   106	112	115	finally
      }
      
      /* Error */
      public void e(do paramdo, int paramInt, String paramString, Bundle paramBundle)
        throws RemoteException
      {
        // Byte code:
        //   0: invokestatic 25	android/os/Parcel:obtain	()Landroid/os/Parcel;
        //   3: astore 5
        //   5: invokestatic 25	android/os/Parcel:obtain	()Landroid/os/Parcel;
        //   8: astore 6
        //   10: aload 5
        //   12: ldc 27
        //   14: invokevirtual 31	android/os/Parcel:writeInterfaceToken	(Ljava/lang/String;)V
        //   17: aload_1
        //   18: ifnull +82 -> 100
        //   21: aload_1
        //   22: invokeinterface 37 1 0
        //   27: astore 8
        //   29: aload 5
        //   31: aload 8
        //   33: invokevirtual 40	android/os/Parcel:writeStrongBinder	(Landroid/os/IBinder;)V
        //   36: aload 5
        //   38: iload_2
        //   39: invokevirtual 44	android/os/Parcel:writeInt	(I)V
        //   42: aload 5
        //   44: aload_3
        //   45: invokevirtual 60	android/os/Parcel:writeString	(Ljava/lang/String;)V
        //   48: aload 4
        //   50: ifnull +56 -> 106
        //   53: aload 5
        //   55: iconst_1
        //   56: invokevirtual 44	android/os/Parcel:writeInt	(I)V
        //   59: aload 4
        //   61: aload 5
        //   63: iconst_0
        //   64: invokevirtual 67	android/os/Bundle:writeToParcel	(Landroid/os/Parcel;I)V
        //   67: aload_0
        //   68: getfield 15	com/google/android/gms/internal/dp$a$a:dG	Landroid/os/IBinder;
        //   71: bipush 8
        //   73: aload 5
        //   75: aload 6
        //   77: iconst_0
        //   78: invokeinterface 50 5 0
        //   83: pop
        //   84: aload 6
        //   86: invokevirtual 53	android/os/Parcel:readException	()V
        //   89: aload 6
        //   91: invokevirtual 56	android/os/Parcel:recycle	()V
        //   94: aload 5
        //   96: invokevirtual 56	android/os/Parcel:recycle	()V
        //   99: return
        //   100: aconst_null
        //   101: astore 8
        //   103: goto -74 -> 29
        //   106: aload 5
        //   108: iconst_0
        //   109: invokevirtual 44	android/os/Parcel:writeInt	(I)V
        //   112: goto -45 -> 67
        //   115: astore 7
        //   117: aload 6
        //   119: invokevirtual 56	android/os/Parcel:recycle	()V
        //   122: aload 5
        //   124: invokevirtual 56	android/os/Parcel:recycle	()V
        //   127: aload 7
        //   129: athrow
        // Local variable table:
        //   start	length	slot	name	signature
        //   0	130	0	this	a
        //   0	130	1	paramdo	do
        //   0	130	2	paramInt	int
        //   0	130	3	paramString	String
        //   0	130	4	paramBundle	Bundle
        //   3	120	5	localParcel1	Parcel
        //   8	110	6	localParcel2	Parcel
        //   115	13	7	localObject	Object
        //   27	75	8	localIBinder	IBinder
        // Exception table:
        //   from	to	target	type
        //   10	17	115	finally
        //   21	29	115	finally
        //   29	48	115	finally
        //   53	67	115	finally
        //   67	89	115	finally
        //   106	112	115	finally
      }
      
      /* Error */
      public void f(do paramdo, int paramInt, String paramString, Bundle paramBundle)
        throws RemoteException
      {
        // Byte code:
        //   0: invokestatic 25	android/os/Parcel:obtain	()Landroid/os/Parcel;
        //   3: astore 5
        //   5: invokestatic 25	android/os/Parcel:obtain	()Landroid/os/Parcel;
        //   8: astore 6
        //   10: aload 5
        //   12: ldc 27
        //   14: invokevirtual 31	android/os/Parcel:writeInterfaceToken	(Ljava/lang/String;)V
        //   17: aload_1
        //   18: ifnull +82 -> 100
        //   21: aload_1
        //   22: invokeinterface 37 1 0
        //   27: astore 8
        //   29: aload 5
        //   31: aload 8
        //   33: invokevirtual 40	android/os/Parcel:writeStrongBinder	(Landroid/os/IBinder;)V
        //   36: aload 5
        //   38: iload_2
        //   39: invokevirtual 44	android/os/Parcel:writeInt	(I)V
        //   42: aload 5
        //   44: aload_3
        //   45: invokevirtual 60	android/os/Parcel:writeString	(Ljava/lang/String;)V
        //   48: aload 4
        //   50: ifnull +56 -> 106
        //   53: aload 5
        //   55: iconst_1
        //   56: invokevirtual 44	android/os/Parcel:writeInt	(I)V
        //   59: aload 4
        //   61: aload 5
        //   63: iconst_0
        //   64: invokevirtual 67	android/os/Bundle:writeToParcel	(Landroid/os/Parcel;I)V
        //   67: aload_0
        //   68: getfield 15	com/google/android/gms/internal/dp$a$a:dG	Landroid/os/IBinder;
        //   71: bipush 11
        //   73: aload 5
        //   75: aload 6
        //   77: iconst_0
        //   78: invokeinterface 50 5 0
        //   83: pop
        //   84: aload 6
        //   86: invokevirtual 53	android/os/Parcel:readException	()V
        //   89: aload 6
        //   91: invokevirtual 56	android/os/Parcel:recycle	()V
        //   94: aload 5
        //   96: invokevirtual 56	android/os/Parcel:recycle	()V
        //   99: return
        //   100: aconst_null
        //   101: astore 8
        //   103: goto -74 -> 29
        //   106: aload 5
        //   108: iconst_0
        //   109: invokevirtual 44	android/os/Parcel:writeInt	(I)V
        //   112: goto -45 -> 67
        //   115: astore 7
        //   117: aload 6
        //   119: invokevirtual 56	android/os/Parcel:recycle	()V
        //   122: aload 5
        //   124: invokevirtual 56	android/os/Parcel:recycle	()V
        //   127: aload 7
        //   129: athrow
        // Local variable table:
        //   start	length	slot	name	signature
        //   0	130	0	this	a
        //   0	130	1	paramdo	do
        //   0	130	2	paramInt	int
        //   0	130	3	paramString	String
        //   0	130	4	paramBundle	Bundle
        //   3	120	5	localParcel1	Parcel
        //   8	110	6	localParcel2	Parcel
        //   115	13	7	localObject	Object
        //   27	75	8	localIBinder	IBinder
        // Exception table:
        //   from	to	target	type
        //   10	17	115	finally
        //   21	29	115	finally
        //   29	48	115	finally
        //   53	67	115	finally
        //   67	89	115	finally
        //   106	112	115	finally
      }
      
      /* Error */
      public void g(do paramdo, int paramInt, String paramString, Bundle paramBundle)
        throws RemoteException
      {
        // Byte code:
        //   0: invokestatic 25	android/os/Parcel:obtain	()Landroid/os/Parcel;
        //   3: astore 5
        //   5: invokestatic 25	android/os/Parcel:obtain	()Landroid/os/Parcel;
        //   8: astore 6
        //   10: aload 5
        //   12: ldc 27
        //   14: invokevirtual 31	android/os/Parcel:writeInterfaceToken	(Ljava/lang/String;)V
        //   17: aload_1
        //   18: ifnull +82 -> 100
        //   21: aload_1
        //   22: invokeinterface 37 1 0
        //   27: astore 8
        //   29: aload 5
        //   31: aload 8
        //   33: invokevirtual 40	android/os/Parcel:writeStrongBinder	(Landroid/os/IBinder;)V
        //   36: aload 5
        //   38: iload_2
        //   39: invokevirtual 44	android/os/Parcel:writeInt	(I)V
        //   42: aload 5
        //   44: aload_3
        //   45: invokevirtual 60	android/os/Parcel:writeString	(Ljava/lang/String;)V
        //   48: aload 4
        //   50: ifnull +56 -> 106
        //   53: aload 5
        //   55: iconst_1
        //   56: invokevirtual 44	android/os/Parcel:writeInt	(I)V
        //   59: aload 4
        //   61: aload 5
        //   63: iconst_0
        //   64: invokevirtual 67	android/os/Bundle:writeToParcel	(Landroid/os/Parcel;I)V
        //   67: aload_0
        //   68: getfield 15	com/google/android/gms/internal/dp$a$a:dG	Landroid/os/IBinder;
        //   71: bipush 12
        //   73: aload 5
        //   75: aload 6
        //   77: iconst_0
        //   78: invokeinterface 50 5 0
        //   83: pop
        //   84: aload 6
        //   86: invokevirtual 53	android/os/Parcel:readException	()V
        //   89: aload 6
        //   91: invokevirtual 56	android/os/Parcel:recycle	()V
        //   94: aload 5
        //   96: invokevirtual 56	android/os/Parcel:recycle	()V
        //   99: return
        //   100: aconst_null
        //   101: astore 8
        //   103: goto -74 -> 29
        //   106: aload 5
        //   108: iconst_0
        //   109: invokevirtual 44	android/os/Parcel:writeInt	(I)V
        //   112: goto -45 -> 67
        //   115: astore 7
        //   117: aload 6
        //   119: invokevirtual 56	android/os/Parcel:recycle	()V
        //   122: aload 5
        //   124: invokevirtual 56	android/os/Parcel:recycle	()V
        //   127: aload 7
        //   129: athrow
        // Local variable table:
        //   start	length	slot	name	signature
        //   0	130	0	this	a
        //   0	130	1	paramdo	do
        //   0	130	2	paramInt	int
        //   0	130	3	paramString	String
        //   0	130	4	paramBundle	Bundle
        //   3	120	5	localParcel1	Parcel
        //   8	110	6	localParcel2	Parcel
        //   115	13	7	localObject	Object
        //   27	75	8	localIBinder	IBinder
        // Exception table:
        //   from	to	target	type
        //   10	17	115	finally
        //   21	29	115	finally
        //   29	48	115	finally
        //   53	67	115	finally
        //   67	89	115	finally
        //   106	112	115	finally
      }
      
      /* Error */
      public void h(do paramdo, int paramInt, String paramString, Bundle paramBundle)
        throws RemoteException
      {
        // Byte code:
        //   0: invokestatic 25	android/os/Parcel:obtain	()Landroid/os/Parcel;
        //   3: astore 5
        //   5: invokestatic 25	android/os/Parcel:obtain	()Landroid/os/Parcel;
        //   8: astore 6
        //   10: aload 5
        //   12: ldc 27
        //   14: invokevirtual 31	android/os/Parcel:writeInterfaceToken	(Ljava/lang/String;)V
        //   17: aload_1
        //   18: ifnull +82 -> 100
        //   21: aload_1
        //   22: invokeinterface 37 1 0
        //   27: astore 8
        //   29: aload 5
        //   31: aload 8
        //   33: invokevirtual 40	android/os/Parcel:writeStrongBinder	(Landroid/os/IBinder;)V
        //   36: aload 5
        //   38: iload_2
        //   39: invokevirtual 44	android/os/Parcel:writeInt	(I)V
        //   42: aload 5
        //   44: aload_3
        //   45: invokevirtual 60	android/os/Parcel:writeString	(Ljava/lang/String;)V
        //   48: aload 4
        //   50: ifnull +56 -> 106
        //   53: aload 5
        //   55: iconst_1
        //   56: invokevirtual 44	android/os/Parcel:writeInt	(I)V
        //   59: aload 4
        //   61: aload 5
        //   63: iconst_0
        //   64: invokevirtual 67	android/os/Bundle:writeToParcel	(Landroid/os/Parcel;I)V
        //   67: aload_0
        //   68: getfield 15	com/google/android/gms/internal/dp$a$a:dG	Landroid/os/IBinder;
        //   71: bipush 13
        //   73: aload 5
        //   75: aload 6
        //   77: iconst_0
        //   78: invokeinterface 50 5 0
        //   83: pop
        //   84: aload 6
        //   86: invokevirtual 53	android/os/Parcel:readException	()V
        //   89: aload 6
        //   91: invokevirtual 56	android/os/Parcel:recycle	()V
        //   94: aload 5
        //   96: invokevirtual 56	android/os/Parcel:recycle	()V
        //   99: return
        //   100: aconst_null
        //   101: astore 8
        //   103: goto -74 -> 29
        //   106: aload 5
        //   108: iconst_0
        //   109: invokevirtual 44	android/os/Parcel:writeInt	(I)V
        //   112: goto -45 -> 67
        //   115: astore 7
        //   117: aload 6
        //   119: invokevirtual 56	android/os/Parcel:recycle	()V
        //   122: aload 5
        //   124: invokevirtual 56	android/os/Parcel:recycle	()V
        //   127: aload 7
        //   129: athrow
        // Local variable table:
        //   start	length	slot	name	signature
        //   0	130	0	this	a
        //   0	130	1	paramdo	do
        //   0	130	2	paramInt	int
        //   0	130	3	paramString	String
        //   0	130	4	paramBundle	Bundle
        //   3	120	5	localParcel1	Parcel
        //   8	110	6	localParcel2	Parcel
        //   115	13	7	localObject	Object
        //   27	75	8	localIBinder	IBinder
        // Exception table:
        //   from	to	target	type
        //   10	17	115	finally
        //   21	29	115	finally
        //   29	48	115	finally
        //   53	67	115	finally
        //   67	89	115	finally
        //   106	112	115	finally
      }
      
      /* Error */
      public void i(do paramdo, int paramInt, String paramString, Bundle paramBundle)
        throws RemoteException
      {
        // Byte code:
        //   0: invokestatic 25	android/os/Parcel:obtain	()Landroid/os/Parcel;
        //   3: astore 5
        //   5: invokestatic 25	android/os/Parcel:obtain	()Landroid/os/Parcel;
        //   8: astore 6
        //   10: aload 5
        //   12: ldc 27
        //   14: invokevirtual 31	android/os/Parcel:writeInterfaceToken	(Ljava/lang/String;)V
        //   17: aload_1
        //   18: ifnull +82 -> 100
        //   21: aload_1
        //   22: invokeinterface 37 1 0
        //   27: astore 8
        //   29: aload 5
        //   31: aload 8
        //   33: invokevirtual 40	android/os/Parcel:writeStrongBinder	(Landroid/os/IBinder;)V
        //   36: aload 5
        //   38: iload_2
        //   39: invokevirtual 44	android/os/Parcel:writeInt	(I)V
        //   42: aload 5
        //   44: aload_3
        //   45: invokevirtual 60	android/os/Parcel:writeString	(Ljava/lang/String;)V
        //   48: aload 4
        //   50: ifnull +56 -> 106
        //   53: aload 5
        //   55: iconst_1
        //   56: invokevirtual 44	android/os/Parcel:writeInt	(I)V
        //   59: aload 4
        //   61: aload 5
        //   63: iconst_0
        //   64: invokevirtual 67	android/os/Bundle:writeToParcel	(Landroid/os/Parcel;I)V
        //   67: aload_0
        //   68: getfield 15	com/google/android/gms/internal/dp$a$a:dG	Landroid/os/IBinder;
        //   71: bipush 14
        //   73: aload 5
        //   75: aload 6
        //   77: iconst_0
        //   78: invokeinterface 50 5 0
        //   83: pop
        //   84: aload 6
        //   86: invokevirtual 53	android/os/Parcel:readException	()V
        //   89: aload 6
        //   91: invokevirtual 56	android/os/Parcel:recycle	()V
        //   94: aload 5
        //   96: invokevirtual 56	android/os/Parcel:recycle	()V
        //   99: return
        //   100: aconst_null
        //   101: astore 8
        //   103: goto -74 -> 29
        //   106: aload 5
        //   108: iconst_0
        //   109: invokevirtual 44	android/os/Parcel:writeInt	(I)V
        //   112: goto -45 -> 67
        //   115: astore 7
        //   117: aload 6
        //   119: invokevirtual 56	android/os/Parcel:recycle	()V
        //   122: aload 5
        //   124: invokevirtual 56	android/os/Parcel:recycle	()V
        //   127: aload 7
        //   129: athrow
        // Local variable table:
        //   start	length	slot	name	signature
        //   0	130	0	this	a
        //   0	130	1	paramdo	do
        //   0	130	2	paramInt	int
        //   0	130	3	paramString	String
        //   0	130	4	paramBundle	Bundle
        //   3	120	5	localParcel1	Parcel
        //   8	110	6	localParcel2	Parcel
        //   115	13	7	localObject	Object
        //   27	75	8	localIBinder	IBinder
        // Exception table:
        //   from	to	target	type
        //   10	17	115	finally
        //   21	29	115	finally
        //   29	48	115	finally
        //   53	67	115	finally
        //   67	89	115	finally
        //   106	112	115	finally
      }
      
      /* Error */
      public void j(do paramdo, int paramInt, String paramString, Bundle paramBundle)
        throws RemoteException
      {
        // Byte code:
        //   0: invokestatic 25	android/os/Parcel:obtain	()Landroid/os/Parcel;
        //   3: astore 5
        //   5: invokestatic 25	android/os/Parcel:obtain	()Landroid/os/Parcel;
        //   8: astore 6
        //   10: aload 5
        //   12: ldc 27
        //   14: invokevirtual 31	android/os/Parcel:writeInterfaceToken	(Ljava/lang/String;)V
        //   17: aload_1
        //   18: ifnull +82 -> 100
        //   21: aload_1
        //   22: invokeinterface 37 1 0
        //   27: astore 8
        //   29: aload 5
        //   31: aload 8
        //   33: invokevirtual 40	android/os/Parcel:writeStrongBinder	(Landroid/os/IBinder;)V
        //   36: aload 5
        //   38: iload_2
        //   39: invokevirtual 44	android/os/Parcel:writeInt	(I)V
        //   42: aload 5
        //   44: aload_3
        //   45: invokevirtual 60	android/os/Parcel:writeString	(Ljava/lang/String;)V
        //   48: aload 4
        //   50: ifnull +56 -> 106
        //   53: aload 5
        //   55: iconst_1
        //   56: invokevirtual 44	android/os/Parcel:writeInt	(I)V
        //   59: aload 4
        //   61: aload 5
        //   63: iconst_0
        //   64: invokevirtual 67	android/os/Bundle:writeToParcel	(Landroid/os/Parcel;I)V
        //   67: aload_0
        //   68: getfield 15	com/google/android/gms/internal/dp$a$a:dG	Landroid/os/IBinder;
        //   71: bipush 15
        //   73: aload 5
        //   75: aload 6
        //   77: iconst_0
        //   78: invokeinterface 50 5 0
        //   83: pop
        //   84: aload 6
        //   86: invokevirtual 53	android/os/Parcel:readException	()V
        //   89: aload 6
        //   91: invokevirtual 56	android/os/Parcel:recycle	()V
        //   94: aload 5
        //   96: invokevirtual 56	android/os/Parcel:recycle	()V
        //   99: return
        //   100: aconst_null
        //   101: astore 8
        //   103: goto -74 -> 29
        //   106: aload 5
        //   108: iconst_0
        //   109: invokevirtual 44	android/os/Parcel:writeInt	(I)V
        //   112: goto -45 -> 67
        //   115: astore 7
        //   117: aload 6
        //   119: invokevirtual 56	android/os/Parcel:recycle	()V
        //   122: aload 5
        //   124: invokevirtual 56	android/os/Parcel:recycle	()V
        //   127: aload 7
        //   129: athrow
        // Local variable table:
        //   start	length	slot	name	signature
        //   0	130	0	this	a
        //   0	130	1	paramdo	do
        //   0	130	2	paramInt	int
        //   0	130	3	paramString	String
        //   0	130	4	paramBundle	Bundle
        //   3	120	5	localParcel1	Parcel
        //   8	110	6	localParcel2	Parcel
        //   115	13	7	localObject	Object
        //   27	75	8	localIBinder	IBinder
        // Exception table:
        //   from	to	target	type
        //   10	17	115	finally
        //   21	29	115	finally
        //   29	48	115	finally
        //   53	67	115	finally
        //   67	89	115	finally
        //   106	112	115	finally
      }
    }
  }
}


/* Location:           C:\Cygwin\home\breandan\apk-tool\classes-dex2jar.jar
 * Qualified Name:     com.google.android.gms.internal.dp
 * JD-Core Version:    0.7.0.1
 */